{"nodes": [{"id": "c_users_rafa_esp32_motor_control_pio_libdeps_esp32dev_arduinojson_src_arduinojson_variant_varianttag_hpp", "label": "VariantTag.hpp", "file_type": "code", "source_file": "C:\\Users\\Rafa\\esp32-motor-control\\.pio\\libdeps\\esp32dev\\ArduinoJson\\src\\ArduinoJson\\Variant\\VariantTag.hpp", "source_location": "L1"}, {"id": "variant_varianttag_isvariant", "label": "IsVariant", "file_type": "code", "source_file": "C:\\Users\\Rafa\\esp32-motor-control\\.pio\\libdeps\\esp32dev\\ArduinoJson\\src\\ArduinoJson\\Variant\\VariantTag.hpp", "source_location": "L14"}, {"id": "is_base_of", "label": "is_base_of", "file_type": "code", "source_file": "", "source_location": ""}], "edges": [{"source": "c_users_rafa_esp32_motor_control_pio_libdeps_esp32dev_arduinojson_src_arduinojson_variant_varianttag_hpp", "target": "namespace", "relation": "imports", "context": "import", "confidence": "EXTRACTED", "source_file": "C:\\Users\\Rafa\\esp32-motor-control\\.pio\\libdeps\\esp32dev\\ArduinoJson\\src\\ArduinoJson\\Variant\\VariantTag.hpp", "source_location": "L7", "weight": 1.0}, {"source": "c_users_rafa_esp32_motor_control_pio_libdeps_esp32dev_arduinojson_src_arduinojson_variant_varianttag_hpp", "target": "variant_varianttag_isvariant", "relation": "contains", "confidence": "EXTRACTED", "source_file": "C:\\Users\\Rafa\\esp32-motor-control\\.pio\\libdeps\\esp32dev\\ArduinoJson\\src\\ArduinoJson\\Variant\\VariantTag.hpp", "source_location": "L14", "weight": 1.0}, {"source": "variant_varianttag_isvariant", "target": "is_base_of", "relation": "inherits", "confidence": "EXTRACTED", "source_file": "C:\\Users\\Rafa\\esp32-motor-control\\.pio\\libdeps\\esp32dev\\ArduinoJson\\src\\ArduinoJson\\Variant\\VariantTag.hpp", "source_location": "L14", "weight": 1.0}], "raw_calls": []}